[{"name":"레프티","address":"인천 남동구 백범로180번길 90 1층 레프티베이커리","cuisine":"베이커리","website":"https://www.instagram.com/lefty_bakery","description":"빵이 맛있다","id":"9fd0da32-cdde-4ff2-8987-855640413eb8"},{"name":"스시민 구월점","address":"인천 남동구 인하로 556","cuisine":"일식","website":"https://www.instagram.com/ichibankorea_official/","description":"음식이 맛있다","id":"b02e1484-6bbc-4377-88e2-1c3f3597ba34"},{"name":"차이홍","address":"인천 남동구 독점로29번길 24 103호 차이홍","cuisine":"중식","website":"https://blog.naver.com/eju9692","description":"양이 많아요","id":"ff23117a-9c2f-461a-aa44-d4b074ad8185"},{"name":"그라나다","address":"인천 남동구 성말로32번길 26 1층","cuisine":"양식","website":"http://instagram.com/guwol_granada032","description":"인테리어가 멋지다","id":"146b934b-ad0c-41a6-a649-1f557d723b2b"}]